ohlcv/__init__.py
ohlcv/ohlcv.py
ohlcv/utils.py
ohlcv_plus-2.0.3.dist-info/LICENSE
ohlcv_plus-2.0.3.dist-info/METADATA
ohlcv_plus-2.0.3.dist-info/WHEEL
ohlcv_plus-2.0.3.dist-info/top_level.txt
ohlcv_plus-2.0.3.dist-info/RECORD
